Leer_PDFR370/Funciones.py
Leer_PDFR370/__init__.py
Leer_PDFR370-3.7.1.dist-info/METADATA
Leer_PDFR370-3.7.1.dist-info/WHEEL
Leer_PDFR370-3.7.1.dist-info/top_level.txt
Leer_PDFR370-3.7.1.dist-info/RECORD
