Metadata-Version: 2.1
Name: Leer-PDFR370
Version: 3.7.1
Summary: Librería para leer ficheros PDFs y extraer la información en formato str
Home-page: https://github.com/Rlimon3702/
Author: R Limon
Author-email: rlimon.tva@gmail.com
License: MIT
Requires-Dist: pymupdf
